{
  "family": "pa-study-hub-frontend",
  "networkMode": "awsvpc",
  "requiresCompatibilities": ["FARGATE"],
  "cpu": "256",
  "memory": "512",
  "executionRoleArn": "arn:aws:iam::ACCOUNT_ID:role/pa-study-hub-task-execution-role",
  "taskRoleArn": "arn:aws:iam::ACCOUNT_ID:role/pa-study-hub-task-role",
  "containerDefinitions": [
    {
      "name": "frontend",
      "image": "ACCOUNT_ID.dkr.ecr.REGION.amazonaws.com/pa-study-hub/frontend:latest",
      "essential": true,
      "portMappings": [
        {
          "containerPort": 80,
          "protocol": "tcp"
        }
      ],
      "healthCheck": {
        "command": ["CMD-SHELL", "wget -q --spider http://localhost:80/health || exit 1"],
        "interval": 30,
        "timeout": 5,
        "retries": 3,
        "startPeriod": 10
      },
      "logConfiguration": {
        "logDriver": "awslogs",
        "options": {
          "awslogs-group":         "/ecs/pa-study-hub/frontend",
          "awslogs-region":        "REGION",
          "awslogs-stream-prefix": "ecs"
        }
      }
    }
  ]
}
